{
  

    "project1-2018-12-02-e6-b5-8b-e8-af-95": {
      "title": "hello world",
      "content"	 : "github搭建博客创建仓库首先你得有一个Github账号，没有的话去github.com注册一个账号，然后到达仓库信息填写界面：创建仓库，如下图：（仓库名要以自己的github名作为前缀，后面的夹 .github.io ）后点击create repository 创建，然后到设置界面在设置界面中找到Choose a theme选项点击上面的都是github给我们提供的一些样例模板，随便选择一个。选择完毕之后我们提交更改，我们点击提交。提交之后，恭喜你，你的网站可以访问了， 访问地址  用户名.github.io设置域名这样的用户名看起来有点不爽，你也可以修改的哦，改成自己的域名   .com .cn 等。可以在阿里云上购买阿里云域名。（ps: 像.win、.top，.site这样的域名现在来说相当便宜，几块钱就能购买到一年的使用权限）购买流程就不说了，购买之后。打开控制台，点击解析域名，如图：点击解析之后，选择CNAME，改成jjjfew.github.io地址即可，如图所示：设置主页之后你可以把你的仓库的文件全部删除，换成自己的写的网站，当然只能是 静态的哦， 还得有个index文件访问入口,github搭建个人博客———-绑定域名访问 - 切切歆语 - 博客园",
      "url": "//project1/2018/12/02/%E6%B5%8B%E8%AF%95/",
      "author": "guchen",
      "categories": "project1"
    }
    
  

  
    
  
    
  
    
  
    
  
    
  
    
  
    
  
    
  
    
  
    
  
    
  
    
  
}